quri_parts/chem/NOTICE
quri_parts/chem/ansatz/__init__.py
quri_parts/chem/ansatz/all_singles_doubles.py
quri_parts/chem/ansatz/gate_fabric.py
quri_parts/chem/ansatz/particle_conserving_u1.py
quri_parts/chem/ansatz/particle_conserving_u2.py
quri_parts/chem/mol/__init__.py
quri_parts/chem/mol/active_space.py
quri_parts/chem/mol/models.py
quri_parts/chem/mol/non_relativistic_models.py
quri_parts/chem/properties/__init__.py
quri_parts/chem/py.typed
quri_parts/chem/transforms/__init__.py
quri_parts/chem/utils/excitations.py
quri_parts/chem/utils/orbital_rotation.py
quri_parts/chem/utils/spin.py
quri_parts_chem-17.0.0.dist-info/LICENSE
quri_parts_chem-17.0.0.dist-info/METADATA
quri_parts_chem-17.0.0.dist-info/WHEEL
quri_parts_chem-17.0.0.dist-info/RECORD
